pnw_subscriptions/__init__.py
pnw_subscriptions/node_manager.py
pnw_subscriptions/subscriptions.py
pnw_subscriptions/scripts/generic_listener.js
pnw_subscriptions-0.2.4.dist-info/METADATA
pnw_subscriptions-0.2.4.dist-info/WHEEL
pnw_subscriptions-0.2.4.dist-info/top_level.txt
pnw_subscriptions-0.2.4.dist-info/RECORD
